README.rst
setup.py
dns_batch_resolver/__init__.py
dns_batch_resolver/cleanup.py
dns_batch_resolver/config.py
dns_batch_resolver/db.py
dns_batch_resolver/log.py
dns_batch_resolver/qdns.py
dns_batch_resolver/query.py
dns_batch_resolver/resolv.py
dns_batch_resolver/suxreadline.py
dns_batch_resolver/tst_yml.py
dns_batch_resolver.egg-info/PKG-INFO
dns_batch_resolver.egg-info/SOURCES.txt
dns_batch_resolver.egg-info/dependency_links.txt
dns_batch_resolver.egg-info/requires.txt
dns_batch_resolver.egg-info/top_level.txt
utils/__dns_batch_resolver.py
utils/dns_batch_resolver