Metadata-Version: 1.1
Name: dns-batch-resolver
Version: 0.0.2
Summary: "Framework" for running a lot of twitterbots without useless twitter API calls.
Home-page: https://github.com/strizhechenko/dns_batch_resolver
Author: Oleg Strizhechenko
Author-email: oleg.strizhechenko@gmail.com
License: GPL
Keywords: dns batch resolver multithreaded ipv6 multiple servers
Platform: UNKNOWN
Classifier: Development Status :: 3 - Alpha
Classifier: Intended Audience :: Developers
Classifier: Operating System :: MacOS
Classifier: Operating System :: POSIX
Classifier: Programming Language :: Python
Classifier: Programming Language :: Python :: 2
Classifier: Topic :: Software Development
Classifier: Topic :: Utilities
